[
  {
    "pkmNo": 26,
    "pokemon": "Raichu",
    "ability": "linghtning-rod",
    "EVStrat": [
      {
        "attack":252,
        "speed":252,
        "hp":6
      }
    ],
  "moves": ["thunderpunch", "thief", "protect", "trailblaze"],
    "item": "quick claw"
  },
  {
    "pkmNo": 184,
    "pokemon": "Azumarill",
    "ability": "huge power",
    "EVStrat": [
      {
        "attack":252,
        "speed":252,
        "hp":6
      }
    ],
  "moves": ["aqua jet", "play rough", "bellydrum", "liquidation"],
    "item": "sitrus berry"
  }
]
